rtl/alu.v
`timescale 1ns / 1ps

module alu (
    input  [7:0] A,
    input  [7:0] B,
    input  [3:0] opcode,
    input        enable,

    output reg [7:0] result,
    output reg zero,
    output reg carry,
    output reg negative,
    output reg overflow
);

reg [8:0] temp;

always @(*) begin

    // Default values
    result   = 8'b00000000;
    zero     = 0;
    carry    = 0;
    negative = 0;
    overflow = 0;
    temp     = 9'b0;

    // Low-power concept
    // If enable = 0, ALU remains idle
    if(enable == 0) begin
        result = 8'b00000000;
    end

    else begin

        case(opcode)

            // ADD
            4'b0000: begin
                temp = A + B;
                result = temp[7:0];
                carry = temp[8];

                overflow =
                (~A[7] & ~B[7] & result[7]) |
                ( A[7] &  B[7] & ~result[7]);
            end

            // SUB
            4'b0001: begin
                temp = A - B;
                result = temp[7:0];
                carry = temp[8];

                overflow =
                (~A[7] & B[7] & result[7]) |
                ( A[7] & ~B[7] & ~result[7]);
            end

            // AND
            4'b0010:
                result = A & B;

            // OR
            4'b0011:
                result = A | B;

            // XOR
            4'b0100:
                result = A ^ B;

            // NOT A
            4'b0101:
                result = ~A;

            // Shift Left
            4'b0110:
                result = A << 1;

            // Shift Right
            4'b0111:
                result = A >> 1;

            // Increment
            4'b1000: begin
                temp = A + 1;
                result = temp[7:0];
                carry = temp[8];
            end

            // Decrement
            4'b1001: begin
                temp = A - 1;
                result = temp[7:0];
                carry = temp[8];
            end

            // Compare A and B
            4'b1010: begin

                if(A > B)
                    result = 8'b00000001;

                else if(A == B)
                    result = 8'b00000000;

                else
                    result = 8'b11111111;

            end

            default:
                result = 8'b00000000;

        endcase
    end

    // Zero Flag
    if(result == 8'b00000000)
        zero = 1;

    // Negative Flag
    negative = result[7];

end

endmodule

tb/alu_tb.v
`timescale 1ns / 1ps

module alu_tb;

reg [7:0] A;
reg [7:0] B;
reg [3:0] opcode;
reg enable;

wire [7:0] result;
wire zero;
wire carry;
wire negative;
wire overflow;

alu DUT (
    .A(A),
    .B(B),
    .opcode(opcode),
    .enable(enable),
    .result(result),
    .zero(zero),
    .carry(carry),
    .negative(negative),
    .overflow(overflow)
);

initial begin

    // Generate VCD file
    $dumpfile("alu.vcd");
    $dumpvars(0, alu_tb);

    $display("===== LOW POWER ALU TEST START =====");

    enable = 1;

    // ADD
    A = 8'd10;
    B = 8'd5;
    opcode = 4'b0000;
    #10;

    // SUB
    A = 8'd20;
    B = 8'd8;
    opcode = 4'b0001;
    #10;

    // AND
    A = 8'b11001100;
    B = 8'b10101010;
    opcode = 4'b0010;
    #10;

    // OR
    opcode = 4'b0011;
    #10;

    // XOR
    opcode = 4'b0100;
    #10;

    // NOT
    A = 8'b11110000;
    opcode = 4'b0101;
    #10;

    // Shift Left
    A = 8'b00001111;
    opcode = 4'b0110;
    #10;

    // Shift Right
    opcode = 4'b0111;
    #10;

    // Increment
    A = 8'd99;
    opcode = 4'b1000;
    #10;

    // Decrement
    opcode = 4'b1001;
    #10;

    // Compare A>B
    A = 8'd20;
    B = 8'd10;
    opcode = 4'b1010;
    #10;

    // Compare A=B
    A = 8'd15;
    B = 8'd15;
    opcode = 4'b1010;
    #10;

    // Compare A<B
    A = 8'd5;
    B = 8'd25;
    opcode = 4'b1010;
    #10;

    // Low Power Mode Check
    enable = 0;
    A = 8'd100;
    B = 8'd50;
    opcode = 4'b0000;
    #10;

    $display("===== TEST COMPLETE =====");

    $finish;

end

initial begin
    $monitor(
    "Time=%0t A=%d B=%d OPC=%b Result=%d Zero=%b Carry=%b Neg=%b Overflow=%b",
    $time,A,B,opcode,result,zero,carry,negative,overflow);
end

endmodule

alu.vcd
$date
	Thu Jun 18 00:38:46 2026
$end
$version
	Icarus Verilog
$end
$timescale
	1ps
$end
$scope module alu_tb $end
$var wire 1 ! zero $end
$var wire 8 " result [7:0] $end
$var wire 1 # overflow $end
$var wire 1 $ negative $end
$var wire 1 % carry $end
$var reg 8 & A [7:0] $end
$var reg 8 ' B [7:0] $end
$var reg 1 ( enable $end
$var reg 4 ) opcode [3:0] $end
$scope module DUT $end
$var wire 8 * A [7:0] $end
$var wire 8 + B [7:0] $end
$var wire 1 ( enable $end
$var wire 4 , opcode [3:0] $end
$var reg 1 % carry $end
$var reg 1 $ negative $end
$var reg 1 # overflow $end
$var reg 8 - result [7:0] $end
$var reg 9 . temp [8:0] $end
$var reg 1 ! zero $end
$upscope $end
$upscope $end
$enddefinitions $end
#0
$dumpvars
b1111 .
b1111 -
b0 ,
b101 +
b1010 *
b0 )
1(
b101 '
b1010 &
0%
0$
0#
b1111 "
0!
$end
#10000
b1100 .
b1100 "
b1100 -
b1 )
b1 ,
b1000 '
b1000 +
b10100 &
b10100 *
#20000
1$
b0 .
b10001000 "
b10001000 -
b10 )
b10 ,
b10101010 '
b10101010 +
b11001100 &
b11001100 *
#30000
1$
b11101110 "
b11101110 -
b11 )
b11 ,
#40000
0$
b1100110 "
b1100110 -
b100 )
b100 ,
#50000
b1111 "
b1111 -
b101 )
b101 ,
b11110000 &
b11110000 *
#60000
b11110 "
b11110 -
b110 )
b110 ,
b1111 &
b1111 *
#70000
b111 "
b111 -
b111 )
b111 ,
#80000
b1100100 .
b1100100 "
b1100100 -
b1000 )
b1000 ,
b1100011 &
b1100011 *
#90000
b1100010 .
b1100010 "
b1100010 -
b1001 )
b1001 ,
#100000
b0 .
b1 "
b1 -
b1010 )
b1010 ,
b1010 '
b1010 +
b10100 &
b10100 *
#110000
1!
b0 "
b0 -
b1111 '
b1111 +
b1111 &
b1111 *
#120000
1$
b11111111 "
b11111111 -
0!
b11001 '
b11001 +
b101 &
b101 *
#130000
1!
0$
b0 "
b0 -
b0 )
b0 ,
b110010 '
b110010 +
b1100100 &
b1100100 *
0(
